LICENSE
MANIFEST.in
README.md
requirements.txt
setup.py
seqnmf/__init__.py
seqnmf/dev.py
seqnmf/helpers.py
seqnmf/seqnmf.py
seqnmf.egg-info/PKG-INFO
seqnmf.egg-info/SOURCES.txt
seqnmf.egg-info/dependency_links.txt
seqnmf.egg-info/requires.txt
seqnmf.egg-info/top_level.txt
seqnmf/data/MackeviciusData.mat