Metadata-Version: 1.0
Name: seqnmf
Version: 0.1.2
Summary: Python implementation of seqNMF
Home-page: https://www.context-lab.com
Author: Contextual Dynamics Laboratory
Author-email: contextualdynamics@gmail.com
License: MIT License
